{
  "liga1": [
    {
      "rang": 1,
      "team": "Pärkli Boys United",
      "sp": "8",
      "s": "8",
      "n": "0",
      "u": "0",
      "gplus": "41",
      "gminus": "7",
      "diff": "+34",
      "fp": "39",
      "pkt": "24"
    },
    {
      "rang": 2,
      "team": "Sunnesite Allstars",
      "sp": "7",
      "s": "4",
      "n": "1",
      "u": "2",
      "gplus": "23",
      "gminus": "15",
      "diff": "+8",
      "fp": "35",
      "pkt": "14"
    },
    {
      "rang": 3,
      "team": "Roter Stern Bollwerk",
      "sp": "7",
      "s": "4",
      "n": "2",
      "u": "1",
      "gplus": "15",
      "gminus": "13",
      "diff": "+2",
      "fp": "35",
      "pkt": "13"
    },
    {
      "rang": 4,
      "team": "International Football Club of Berne",
      "sp": "7",
      "s": "4",
      "n": "3",
      "u": "0",
      "gplus": "28",
      "gminus": "22",
      "diff": "+6",
      "fp": "34",
      "pkt": "12"
    },
    {
      "rang": 5,
      "team": "Obstberg United",
      "sp": "7",
      "s": "3",
      "n": "3",
      "u": "1",
      "gplus": "20",
      "gminus": "17",
      "diff": "+3",
      "fp": "35",
      "pkt": "10"
    },
    {
      "rang": 6,
      "team": "SpVgg Lokomotive",
      "sp": "7",
      "s": "3",
      "n": "4",
      "u": "0",
      "gplus": "15",
      "gminus": "19",
      "diff": "-4",
      "fp": "32",
      "pkt": "9"
    },
    {
      "rang": 7,
      "team": "Deportivo Gordo Cojones",
      "sp": "7",
      "s": "3",
      "n": "4",
      "u": "0",
      "gplus": "10",
      "gminus": "20",
      "diff": "-10",
      "fp": "35",
      "pkt": "9"
    },
    {
      "rang": 8,
      "team": "Dynamo Chop",
      "sp": "7",
      "s": "2",
      "n": "3",
      "u": "2",
      "gplus": "12",
      "gminus": "16",
      "diff": "-4",
      "fp": "35",
      "pkt": "8"
    },
    {
      "rang": 9,
      "team": "Energie Bitzius",
      "sp": "8",
      "s": "2",
      "n": "6",
      "u": "0",
      "gplus": "12",
      "gminus": "26",
      "diff": "-14",
      "fp": "40",
      "pkt": "6"
    },
    {
      "rang": 10,
      "team": "AC Diva",
      "sp": "7",
      "s": "0",
      "n": "7",
      "u": "0",
      "gplus": "8",
      "gminus": "29",
      "diff": "-21",
      "fp": "29",
      "pkt": "0"
    }
  ],
  "liga2": [
    {
      "rang": 1,
      "team": "5ème Etage",
      "sp": "8",
      "s": "6",
      "n": "0",
      "u": "2",
      "gplus": "61",
      "gminus": "10",
      "diff": "+51",
      "fp": "39",
      "pkt": "20"
    },
    {
      "rang": 2,
      "team": "Les Mecs Sportifs",
      "sp": "8",
      "s": "6",
      "n": "2",
      "u": "0",
      "gplus": "25",
      "gminus": "16",
      "diff": "+9",
      "fp": "40",
      "pkt": "18"
    },
    {
      "rang": 3,
      "team": "Spartak Bern FC",
      "sp": "7",
      "s": "5",
      "n": "1",
      "u": "1",
      "gplus": "36",
      "gminus": "13",
      "diff": "+23",
      "fp": "34",
      "pkt": "16"
    },
    {
      "rang": 4,
      "team": "Fortuna Galgenfeld",
      "sp": "7",
      "s": "4",
      "n": "2",
      "u": "1",
      "gplus": "24",
      "gminus": "16",
      "diff": "+8",
      "fp": "35",
      "pkt": "13"
    },
    {
      "rang": 5,
      "team": "Olympique Troissept",
      "sp": "7",
      "s": "3",
      "n": "3",
      "u": "1",
      "gplus": "29",
      "gminus": "16",
      "diff": "+13",
      "fp": "35",
      "pkt": "10"
    },
    {
      "rang": 6,
      "team": "Valti Traktor",
      "sp": "7",
      "s": "2",
      "n": "3",
      "u": "2",
      "gplus": "25",
      "gminus": "23",
      "diff": "+2",
      "fp": "35",
      "pkt": "8"
    },
    {
      "rang": 7,
      "team": "Raclette Rangerz",
      "sp": "7",
      "s": "2",
      "n": "4",
      "u": "1",
      "gplus": "17",
      "gminus": "22",
      "diff": "-5",
      "fp": "35",
      "pkt": "7"
    },
    {
      "rang": 8,
      "team": "BFC Cholewärch Viktoria",
      "sp": "7",
      "s": "2",
      "n": "5",
      "u": "0",
      "gplus": "18",
      "gminus": "36",
      "diff": "-18",
      "fp": "35",
      "pkt": "6"
    },
    {
      "rang": 9,
      "team": "Standfest Breitenrain",
      "sp": "7",
      "s": "2",
      "n": "5",
      "u": "0",
      "gplus": "12",
      "gminus": "37",
      "diff": "-25",
      "fp": "28",
      "pkt": "6"
    },
    {
      "rang": 10,
      "team": "West Bärn United",
      "sp": "7",
      "s": "0",
      "n": "7",
      "u": "0",
      "gplus": "12",
      "gminus": "70",
      "diff": "-58",
      "fp": "35",
      "pkt": "0"
    }
  ],
  "updated": "2026-05-31T06:51:35.820826+00:00"
}